L2.4/slave_fsm.v
module slave_fsm(
    input  wire clk,
    input  wire rst,
    input  wire req,
    input  wire [7:0] data_in,
    output reg  ack,
    output reg [7:0] last_byte
);
    localparam [1:0] S_WAIT = 2'b00;
    localparam [1:0] S_ACK1 = 2'b01;
    localparam [1:0] S_ACK2 = 2'b10;

    reg [1:0] state, next_state;

    always @(posedge clk) begin
        if (rst) begin
            state <= S_WAIT;
            ack <= 1'b0;
            last_byte <= 8'd0;
        end else begin
            state <= next_state;
            ack <= ack;         
            last_byte <= last_byte;
        end
    end

    reg ack_comb;
    reg [7:0] last_byte_comb;

    always @(*) begin
        next_state = state;
        ack_comb = 1'b0;
        last_byte_comb = last_byte;

        case (state)
            S_WAIT: begin
                ack_comb = 1'b0;
                if (req) begin
                    last_byte_comb = data_in;
                    next_state = S_ACK1;
                end else begin
                    next_state = S_WAIT;
                end
            end

            S_ACK1: begin
                ack_comb = 1'b1;
                next_state = S_ACK2;
            end

            S_ACK2: begin
                ack_comb = 1'b1;
                next_state = S_WAIT;
            end

            default: begin
                ack_comb = 1'b0;
                next_state = S_WAIT;
            end
        endcase
    end

    always @(posedge clk) begin
        if (rst) begin
            ack <= 1'b0;
            last_byte <= 8'd0;
        end else begin
            ack <= ack_comb;
            last_byte <= last_byte_comb;
        end
    end

endmodule

L2.4/master_fsm.v
module master_fsm(
    input  wire clk,
    input  wire rst, 
    input  wire ack,
    output reg  req,
    output reg [7:0] data,
    output reg  done
);
    parameter NUM_BYTES = 4;

    reg [7:0] bytes [0:NUM_BYTES-1];
    initial begin
        bytes[0] = 8'hA0;
        bytes[1] = 8'hA1;
        bytes[2] = 8'hA2;
        bytes[3] = 8'hA3;
    end

    localparam [2:0] M_IDLE         = 3'd0;
    localparam [2:0] M_REQ          = 3'd1;
    localparam [2:0] M_WAIT_ACK     = 3'd2;
    localparam [2:0] M_DROP_REQ     = 3'd3;
    localparam [2:0] M_WAIT_ACK_LOW = 3'd4;
    localparam [2:0] M_DONE         = 3'd5;

    reg [2:0] state, next_state;
    integer idx, next_idx;

    always @(posedge clk) begin
        if (rst) begin
            state <= M_IDLE;
            idx <= 0;
            req <= 1'b0;
            data <= 8'd0;
            done <= 1'b0;
        end else begin
            state <= next_state;
            idx <= next_idx;
            req <= req;   
            data <= data; 
            done <= done;
        end
    end

    reg req_comb;
    reg [7:0] data_comb;
    reg done_comb;

    always @(*) begin
        next_state = state;
        next_idx = idx;
        req_comb = 1'b0;
        data_comb = 8'd0;
        done_comb = 1'b0;

        case (state)
            M_IDLE: begin
                next_state = M_REQ;
                next_idx = 0;
            end

            M_REQ: begin
                req_comb = 1'b1;
                data_comb = bytes[idx];
                next_state = M_WAIT_ACK;
            end

            M_WAIT_ACK: begin
                req_comb = 1'b1;
                data_comb = bytes[idx];
                if (ack) begin
                    next_state = M_DROP_REQ;
                    next_idx = idx; 
                end else begin
                    next_state = M_WAIT_ACK;
                end
            end

            M_DROP_REQ: begin
                req_comb = 1'b0;
                data_comb = bytes[idx];
                next_state = M_WAIT_ACK_LOW;
                next_idx = idx + 1;
            end

            M_WAIT_ACK_LOW: begin
                req_comb = 1'b0;
                if (!ack) begin
                    if (next_idx >= NUM_BYTES) begin
                        next_state = M_DONE;
                    end else begin
                        next_state = M_REQ;
                    end
                end else begin
                    next_state = M_WAIT_ACK_LOW;
                end
            end

            M_DONE: begin
                done_comb = 1'b1;
                next_state = M_DONE;
            end

            default: begin
                next_state = M_IDLE;
            end
        endcase
    end

    always @(posedge clk) begin
        if (rst) begin
            req <= 1'b0;
            data <= 8'd0;
            done <= 1'b0;
        end else begin
            req <= req_comb;
            data <= data_comb;
            done <= done_comb;
        end
    end

endmodule

L2.4/link_top.v
module link_top(
    input  wire clk,
    input  wire rst,
    output wire done
);
    wire req;
    wire ack;
    wire [7:0] data;
    wire [7:0] last_byte;

    master_fsm master(
        .clk(clk), .rst(rst), .ack(ack),
        .req(req), .data(data), .done(done)
    );

    slave_fsm slave(
        .clk(clk), .rst(rst), .req(req),
        .data_in(data), .ack(ack), .last_byte(last_byte)
    );

endmodule

L2.4/tb_link_top.v
`timescale 1ns/1ps
module tb_link_top;
    reg clk = 0;
    reg rst = 0;
    wire done;

    link_top dut(.clk(clk), .rst(rst), .done(done));

    always #5 clk = ~clk;

    initial begin
        $dumpfile("dump.vcd");
        $dumpvars(0, tb_link_top);

        rst = 1;
        @(posedge clk);
        @(posedge clk);
        rst = 0;

        $display("time req ack data last_byte done");
        repeat (200) begin
            @(posedge clk);
            $display("%0t %b   %b   %02h   %02h        %b",
                $time,
                dut.master.req,
                dut.slave.ack,
                dut.master.data,
                dut.slave.last_byte,
                done);
            if (done) begin
                $display("Done observed at time %0t", $time);
                @(posedge clk);
                $finish;
            end
        end
        $finish;
    end
endmodule

L2.4/dump.vcd
$date
	Tue Aug 19 16:17:01 2025
$end
$version
	Icarus Verilog
$end
$timescale
	1ps
$end
$scope module tb_link_top $end
$var wire 1 ! done $end
$var reg 1 " clk $end
$var reg 1 # rst $end
$scope module dut $end
$var wire 1 " clk $end
$var wire 1 # rst $end
$var wire 1 $ req $end
$var wire 8 % last_byte [7:0] $end
$var wire 1 ! done $end
$var wire 8 & data [7:0] $end
$var wire 1 ' ack $end
$scope module master $end
$var wire 1 " clk $end
$var wire 1 # rst $end
$var wire 1 ' ack $end
$var parameter 3 ( M_DONE $end
$var parameter 3 ) M_DROP_REQ $end
$var parameter 3 * M_IDLE $end
$var parameter 3 + M_REQ $end
$var parameter 3 , M_WAIT_ACK $end
$var parameter 3 - M_WAIT_ACK_LOW $end
$var parameter 32 . NUM_BYTES $end
$var reg 8 / data [7:0] $end
$var reg 8 0 data_comb [7:0] $end
$var reg 1 ! done $end
$var reg 1 1 done_comb $end
$var reg 3 2 next_state [2:0] $end
$var reg 1 $ req $end
$var reg 1 3 req_comb $end
$var reg 3 4 state [2:0] $end
$var integer 32 5 idx [31:0] $end
$var integer 32 6 next_idx [31:0] $end
$upscope $end
$scope module slave $end
$var wire 1 " clk $end
$var wire 8 7 data_in [7:0] $end
$var wire 1 $ req $end
$var wire 1 # rst $end
$var parameter 2 8 S_ACK1 $end
$var parameter 2 9 S_ACK2 $end
$var parameter 2 : S_WAIT $end
$var reg 1 ' ack $end
$var reg 1 ; ack_comb $end
$var reg 8 < last_byte [7:0] $end
$var reg 8 = last_byte_comb [7:0] $end
$var reg 2 > next_state [1:0] $end
$var reg 2 ? state [1:0] $end
$upscope $end
$upscope $end
$upscope $end
$enddefinitions $end
$comment Show the parameter values. $end
$dumpall
b0 :
b10 9
b1 8
b100 .
b100 -
b10 ,
b1 +
b0 *
b11 )
b101 (
$end
#0
$dumpvars
bx ?
bx >
bx =
bx <
x;
bx 7
bx 6
bx 5
bx 4
03
b0 2
01
b0 0
bx /
x'
bx &
bx %
x$
1#
0"
x!
$end
#5000
b0 =
0;
b0 >
b1 2
b0 6
b0 5
b0 4
0!
b0 &
b0 /
b0 7
0$
b0 ?
b0 %
b0 <
0'
1"
#10000
0"
#15000
0#
1"
#20000
0"
#25000
b10 2
b10100000 0
13
b1 4
1"
#30000
0"
#35000
b1 >
b10100000 =
b10100000 0
13
b10100000 &
b10100000 /
b10100000 7
1$
b10 4
1"
#40000
0"
#45000
b10 >
1;
b0 =
b1 ?
b0 %
b0 <
1"
#50000
0"
#55000
b11 2
b10100000 0
13
b0 >
1;
1'
b10 ?
1"
#60000
0"
#65000
b1 6
b100 2
b10100000 0
03
b1 >
b10100000 =
0;
b11 4
b0 ?
1"
#70000
0"
#75000
b10 >
1;
b1 2
b0 0
b10100000 %
b10100000 <
0'
b1 ?
0$
b1 5
b100 4
1"
#80000
0"
#85000
b0 >
1;
b10 2
b10100001 0
13
b1 4
b10100000 &
b10100000 /
b10100000 7
b10 ?
0'
1"
#90000
0"
#95000
b1 >
b10100001 =
0;
b11 2
b10100001 0
13
1'
b0 ?
b10100001 &
b10100001 /
b10100001 7
1$
b10 4
1"
#100000
0"
#105000
b10 >
1;
b10100000 =
b10 6
b100 2
b10100001 0
03
b11 4
b1 ?
b10100000 %
b10100000 <
1'
1"
#110000
0"
#115000
b0 >
1;
b0 0
b10 ?
0$
b10 5
b100 4
1"
#120000
0"
#125000
0;
b10100001 &
b10100001 /
b10100001 7
b0 ?
1"
#130000
0"
#135000
b1 2
0'
b0 &
b0 /
b0 7
1"
#140000
0"
#145000
b10 2
b10100010 0
13
b1 4
1"
#150000
0"
#155000
b1 >
b10100010 =
b10100010 0
13
b10100010 &
b10100010 /
b10100010 7
1$
b10 4
1"
#160000
0"
#165000
b10 >
1;
b10100000 =
b1 ?
b10100000 %
b10100000 <
1"
#170000
0"
#175000
b11 2
b10100010 0
13
b0 >
1;
1'
b10 ?
1"
#180000
0"
#185000
b11 6
b100 2
b10100010 0
03
b1 >
b10100010 =
0;
b11 4
b0 ?
1"
#190000
0"
#195000
b10 >
1;
b1 2
b0 0
b10100010 %
b10100010 <
0'
b1 ?
0$
b11 5
b100 4
1"
#200000
0"
#205000
b0 >
1;
b10 2
b10100011 0
13
b1 4
b10100010 &
b10100010 /
b10100010 7
b10 ?
0'
1"
#210000
0"
#215000
b1 >
b10100011 =
0;
b11 2
b10100011 0
13
1'
b0 ?
b10100011 &
b10100011 /
b10100011 7
1$
b10 4
1"
#220000
0"
#225000
b10 >
1;
b10100010 =
b100 6
b100 2
b10100011 0
03
b11 4
b1 ?
b10100010 %
b10100010 <
1'
1"
#230000
0"
#235000
b0 >
1;
b0 0
b10 ?
0$
b100 5
b100 4
1"
#240000
0"
#245000
0;
b10100011 &
b10100011 /
b10100011 7
b0 ?
1"
#250000
0"
#255000
b101 2
0'
b0 &
b0 /
b0 7
1"
#260000
0"
#265000
11
b101 4
1"
#270000
0"
#275000
1!
1"
