L2.1/seq_detect_mealy.v
module seq_detect_mealy(
    input  wire clk,
    input  wire rst,
    input  wire din,
    output reg  y 
);

    localparam [1:0] S_A = 2'b00; 
    localparam [1:0] S_B = 2'b01; 
    localparam [1:0] S_C = 2'b10; 
    localparam [1:0] S_D = 2'b11;

    reg [1:0] state, next_state;
    reg       y_next;

    always @(posedge clk) begin
        if (rst) begin
            state <= S_A;
            y     <= 1'b0;
        end else begin
            state <= next_state;
            y     <= y_next;
        end
    end

    always @(*) begin
        next_state = state;
        y_next = 1'b0;

        case (state)
            S_A: begin
                if (din) next_state = S_B;
                else     next_state = S_A;
            end

            S_B: begin
                if (din) next_state = S_C;
                else     next_state = S_A;
            end

            S_C: begin
                if (din) next_state = S_D;
                else     next_state = S_A;
            end

            S_D: begin
                if (din) begin
                    y_next = 1'b1;
                    next_state = S_B;
                end else begin
                    next_state = S_A;
                end
            end

            default: begin
                next_state = S_A;
                y_next = 1'b0;
            end
        endcase
    end

endmodule

L2.1/tb_seq_detect_mealy.v
`timescale 1ns/1ps
module tb_seq_detect_mealy;
    reg clk = 0;
    reg rst = 0;
    reg din = 0;
    wire y;

    reg [10:0] stream;
    integer i;

    seq_detect_mealy dut (
        .clk(clk),
        .rst(rst),
        .din(din),
        .y(y)
    );

    always #5 clk = ~clk;

    initial begin
        $dumpfile("dump.vcd");
        $dumpvars(0, tb_seq_detect_mealy);

        rst = 1;
        @(posedge clk);
        @(posedge clk);
        rst = 0;
        @(posedge clk);

        $display("Time\tclk\tdin\ty");

        stream = 11'b11011011101; 

        for (i = 10; i >= 0; i = i - 1) begin
            din = stream[i];
            @(posedge clk);
            $display("%0t\t%b\t%b\t%b", $time, clk, din, y);
        end

        din = 0;
        @(posedge clk);
        @(posedge clk);
        $finish;
    end
endmodule

L2.1/dump.vcd
$date
	Tue Aug 19 15:16:39 2025
$end
$version
	Icarus Verilog
$end
$timescale
	1ps
$end
$scope module tb_seq_detect_mealy $end
$var wire 1 ! y $end
$var reg 1 " clk $end
$var reg 1 # din $end
$var reg 1 $ rst $end
$var reg 11 % stream [10:0] $end
$var integer 32 & i [31:0] $end
$scope module dut $end
$var wire 1 " clk $end
$var wire 1 # din $end
$var wire 1 $ rst $end
$var parameter 2 ' S_A $end
$var parameter 2 ( S_B $end
$var parameter 2 ) S_C $end
$var parameter 2 * S_D $end
$var reg 2 + next_state [1:0] $end
$var reg 2 , state [1:0] $end
$var reg 1 ! y $end
$var reg 1 - y_next $end
$upscope $end
$upscope $end
$enddefinitions $end
$comment Show the parameter values. $end
$dumpall
b11 *
b10 )
b1 (
b0 '
$end
#0
$dumpvars
0-
bx ,
b0 +
bx &
bx %
1$
0#
0"
x!
$end
#5000
0!
b0 ,
1"
#10000
0"
#15000
0$
1"
#20000
0"
#25000
b1 +
1#
b1010 &
b11011011101 %
1"
#30000
0"
#35000
b10 +
b1 ,
b1001 &
1"
#40000
0"
#45000
b10 ,
b0 +
0#
b1000 &
1"
#50000
0"
#55000
b0 ,
b1 +
1#
b111 &
1"
#60000
0"
#65000
b10 +
b1 ,
b110 &
1"
#70000
0"
#75000
b10 ,
b0 +
0#
b101 &
1"
#80000
0"
#85000
b0 ,
b1 +
1#
b100 &
1"
#90000
0"
#95000
b10 +
b1 ,
b11 &
1"
#100000
0"
#105000
b11 +
b10 ,
b10 &
1"
#110000
0"
#115000
b11 ,
b0 +
0#
b1 &
1"
#120000
0"
#125000
b0 ,
0-
b1 +
1#
b0 &
1"
#130000
0"
#135000
b1 ,
b0 +
0#
b11111111111111111111111111111111 &
1"
#140000
0"
#145000
b0 ,
1"
