L2.3/vending_mealy.v
module vending_mealy(
    input  wire clk,
    input  wire rst,     
    input  wire [1:0] coin, 
    output reg dispense, 
    output reg chg5      
);

    localparam [1:0] T0  = 2'b00;
    localparam [1:0] T5  = 2'b01;
    localparam [1:0] T10 = 2'b10;
    localparam [1:0] T15 = 2'b11;

    reg [1:0] state, next_state;
    reg dispense_next, chg5_next;

    always @(posedge clk) begin
        if (rst) begin
            state    <= T0;
            dispense <= 1'b0;
            chg5     <= 1'b0;
        end else begin
            state    <= next_state;
            dispense <= dispense_next;
            chg5     <= chg5_next;
        end
    end

    always @(*) begin
        next_state = state;
        dispense_next = 1'b0;
        chg5_next = 1'b0;

        case (state)
            T0: begin
                case (coin)
                    2'b01: next_state = T5;      
                    2'b10: next_state = T10;    
                    default: next_state = T0; 
                endcase
            end

            T5: begin
                case (coin)
                    2'b01: next_state = T10;     
                    2'b10: next_state = T15;    
                    default: next_state = T5;
                endcase
            end

            T10: begin
                case (coin)
                    2'b01: next_state = T15;     
                    2'b10: begin                 
                        dispense_next = 1'b1;
                        chg5_next = 1'b0;
                        next_state = T0;
                    end
                    default: next_state = T10;
                endcase
            end

            T15: begin
                case (coin)
                    2'b01: begin                 
                        dispense_next = 1'b1;
                        chg5_next = 1'b0;
                        next_state = T0;
                    end
                    2'b10: begin                 
                        dispense_next = 1'b1;
                        chg5_next = 1'b1;
                        next_state = T0;
                    end
                    default: next_state = T15;
                endcase
            end

            default: begin
                next_state = T0;
                dispense_next = 1'b0;
                chg5_next = 1'b0;
            end
        endcase
    end

endmodule

L2.3/tb_vending_mealy.v
`timescale 1ns/1ps
module tb_vending_mealy;
    reg clk = 0;
    reg rst = 0;
    reg [1:0] coin = 2'b00;
    wire dispense;
    wire chg5;

    vending_mealy dut(.clk(clk), .rst(rst), .coin(coin),
                      .dispense(dispense), .chg5(chg5));

    always #5 clk = ~clk;

    task put5;
    begin
        coin = 2'b01;
        @(posedge clk);
        coin = 2'b00;
        @(posedge clk);
    end
    endtask

    task put10;
    begin
        coin = 2'b10;
        @(posedge clk);
        coin = 2'b00;
        @(posedge clk);
    end
    endtask

    initial begin
        $dumpfile("dump.vcd");
        $dumpvars(0, tb_vending_mealy);
        rst = 1;
        @(posedge clk);
        rst = 0;
        @(posedge clk);

        $display("Test: 10 + 10 -> dispense only");
        put10; put10;
        @(posedge clk); @(posedge clk);

        $display("Test: 5 + 5 + 10 -> dispense only");
        put5; put5; put10;
        @(posedge clk); @(posedge clk);

        $display("Test: 10 + 5 + 10 -> vend + chg5 (25 total)");
        put10; put5; put10;
        @(posedge clk); @(posedge clk);

        $display("Done tests");
        $finish;
    end
endmodule

L2.3/dump.vcd
$date
	Tue Aug 19 16:10:17 2025
$end
$version
	Icarus Verilog
$end
$timescale
	1ps
$end
$scope module tb_vending_mealy $end
$var wire 1 ! dispense $end
$var wire 1 " chg5 $end
$var reg 1 # clk $end
$var reg 2 $ coin [1:0] $end
$var reg 1 % rst $end
$scope module dut $end
$var wire 1 # clk $end
$var wire 2 & coin [1:0] $end
$var wire 1 % rst $end
$var parameter 2 ' T0 $end
$var parameter 2 ( T10 $end
$var parameter 2 ) T15 $end
$var parameter 2 * T5 $end
$var reg 1 " chg5 $end
$var reg 1 + chg5_next $end
$var reg 1 ! dispense $end
$var reg 1 , dispense_next $end
$var reg 2 - next_state [1:0] $end
$var reg 2 . state [1:0] $end
$upscope $end
$scope task put10 $end
$upscope $end
$scope task put5 $end
$upscope $end
$upscope $end
$enddefinitions $end
$comment Show the parameter values. $end
$dumpall
b1 *
b11 )
b10 (
b0 '
$end
#0
$dumpvars
bx .
b0 -
0,
0+
b0 &
1%
b0 $
0#
x"
x!
$end
#5000
0"
0!
b0 .
0%
1#
#10000
0#
#15000
b10 -
b10 $
b10 &
1#
#20000
0#
#25000
b10 .
b10 -
b0 $
b0 &
1#
#30000
0#
#35000
b0 -
1,
b10 $
b10 &
1#
#40000
0#
#45000
1!
b0 .
0,
b0 -
b0 $
b0 &
1#
#50000
0#
#55000
0!
1#
#60000
0#
#65000
1#
#70000
0#
#75000
b1 -
b1 $
b1 &
1#
#80000
0#
#85000
b1 .
b1 -
b0 $
b0 &
1#
#90000
0#
#95000
b10 -
b1 $
b1 &
1#
#100000
0#
#105000
b10 .
b10 -
b0 $
b0 &
1#
#110000
0#
#115000
b0 -
1,
b10 $
b10 &
1#
#120000
0#
#125000
1!
b0 .
0,
b0 -
b0 $
b0 &
1#
#130000
0#
#135000
0!
1#
#140000
0#
#145000
1#
#150000
0#
#155000
b10 -
b10 $
b10 &
1#
#160000
0#
#165000
b10 .
b10 -
b0 $
b0 &
1#
#170000
0#
#175000
b11 -
b1 $
b1 &
1#
#180000
0#
#185000
b11 .
b11 -
b0 $
b0 &
1#
#190000
0#
#195000
b0 -
1+
1,
b10 $
b10 &
1#
#200000
0#
#205000
1"
1!
b0 .
0+
0,
b0 -
b0 $
b0 &
1#
#210000
0#
#215000
0"
0!
1#
